test_banch/main_simulation.v

module genius(
  input clock,
  input [2:0] btn,
  input reset,
  input start, 
  input [9:2] sw,
//begin1
output reg [2:0] State,
output reg [2:0] Next_state,
output reg [3:0] Current_level,
output reg [3:0] Sequence_count,
output reg [3:0] Current_number,
//end
  output reg [6:0] segd0,  
  output reg [6:0] segd1,  
  output reg [6:0] segd2,  
  output reg [6:0] segd3, 
  output reg [9:0] leds    
);

reg [3:0] sequence_count;
wire [1:0] current_number;
my_sequence seq(.current_number(current_number), .sequence_count(sequence_count), .clk(clock), .start(start));

wire [6:0] segd_0; 
dec7seg_2bits dec7_2bits(.x(segd_0), .a(current_number));

reg [3:0] current_level;
wire [6:0] segd_2;
wire [6:0] segd_3;
dec7seg_4bits_hexadec dec7seg_4bits_hexadec0(.y(segd_3), .a(current_level)); // temporario
dec7seg_4bits_hexadec dec7seg_4bits_hexadec1(.y(segd_2), .a(sequence_count)); // temporario
//dec7seg_4bits_1x2 dec7_4bits_1x2(.x(segd_3), .y(segd_2), .a(current_level));

wire is_right_choice;
verify_btn verifier(.is_right_choice(is_right_choice), .btn(btn), .current_number(current_number));

wire was_some_btn_pressed;
recieve_btn_input btn_input(.was_some_btn_pressed(was_some_btn_pressed), .btn(btn));

wire [9:0] shifted_leds;
shift_leds shift(.y(shifted_leds), .x(leds));

reg [2:0] state, next_state;
reg clock_count;

// estados da FSM
parameter reset_game_state = 3'o0;
parameter show_sequence_state = 3'o1;
parameter receive_inputs_state = 3'o2;
parameter add_difficult_state = 3'o3;

parameter seg_off = 7'b0000000;
parameter leds_off = 10'b0000000000;
parameter leds_on = 10'b1111111111;


always @(posedge clock) begin
  if(!reset) begin
      state <= next_state;
      segd1 <= seg_off;
      segd2 <= segd_2;      
      segd3 <= segd_3;

      case (state)
        reset_game_state: begin
          leds <= leds_on;
          segd0 <= seg_off;
          next_state <= state; // mantenha o estado atual
          // Resetar o jogo
          if (start) begin 
            sequence_count <= 4'h0;
            current_level <= 4'h0;
            leds <= 10'h1;
            next_state <= show_sequence_state; // mostre a sequencia de numeros
          end
        end

        show_sequence_state: begin
            segd0 <= segd_0;
            clock_count <= 1'b0;
          if (sequence_count >= current_level) begin
            leds <= 10'h1;
            sequence_count <= 4'h0;
            next_state <= receive_inputs_state;
          end
          else begin
            sequence_count <= sequence_count + 1'b1;
            leds <= shifted_leds;
            next_state <= state; // mantenha o estado atual
          end 
        end
        
        receive_inputs_state: begin
          segd0 <= seg_off;
          if (sequence_count > current_level) begin 
              next_state <= add_difficult_state;
          end
          else begin 
            if(was_some_btn_pressed) begin
              if(is_right_choice) begin
                leds <= shifted_leds;
                sequence_count <= sequence_count + 1'b1;
                next_state <= state; // mantenha o estado atual
              end 
              else begin
                leds <= leds_off;
                next_state <= reset_game_state; // jogador perdeu, resete o jogo
              end
            end
            else begin
              next_state <= state; // mantenha o estado atual
            end 
          end
        end       

        add_difficult_state: begin
          // Aumente a sequência
          segd0 <= seg_off;
          if (current_level < 15 && clock_count == 0) begin 
              clock_count <= clock_count + 1'b1;
              current_level <= current_level + 1'b1;
              next_state <= state; // mantem no mesmo estado
          end
          else if (current_level < 15 && clock_count == 1) begin 
              sequence_count <= 4'h0;
              next_state <= show_sequence_state;
          end
          else begin
              next_state <= reset_game_state; // jogador ganhou, resete o jogo
          end
        end 

        default: begin
          leds <= leds_off;
          next_state <= reset_game_state;     
        end 
      endcase
    end
    else begin
      segd1 <= seg_off;
      leds <= leds_off;
      segd2 <= seg_off;      
      segd3 <= seg_off;
    end
//begin2
State <= state;
Next_state <= next_state;
Current_level <= current_level;
Sequence_count <= sequence_count;
Current_number <= current_number;
//end
  end
endmodule



module my_sequence (
    output reg [1:0] current_number,
    input [3:0] sequence_count,
    input clk,
    input start
);

parameter [1:0] zero = 2'b00;
parameter [1:0] one = 2'b01;
parameter [1:0] two = 2'b10;

reg [1:0] sequence_0;
reg [1:0] sequence_1;
reg [1:0] sequence_2;
reg [1:0] sequence_3;
reg [1:0] sequence_4;
reg [1:0] sequence_5;
reg [1:0] sequence_6;
reg [1:0] sequence_7;
reg [1:0] sequence_8;
reg [1:0] sequence_9;
reg [1:0] sequence_10;
reg [1:0] sequence_11;
reg [1:0] sequence_12;
reg [1:0] sequence_13;
reg [1:0] sequence_14;
reg [1:0] sequence_15;

always @(posedge start) begin 
    sequence_0 <= two;
    sequence_1 <= one;
    sequence_2 <= zero;
    sequence_3 <= one;
    sequence_4 <= zero;
    sequence_5 <= two;
    sequence_6 <= zero;
    sequence_7 <= two;
    sequence_8 <= zero;
    sequence_9 <= one;
    sequence_10 <= zero;
    sequence_11 <= two;
    sequence_12 <= zero;
    sequence_13 <= one;
    sequence_14 <= zero;
    sequence_15 <= one;
end

always @(posedge clk) begin
    case (sequence_count)
        4'h0: current_number <= sequence_0;
        4'h1: current_number <= sequence_1;
        4'h2: current_number <= sequence_2;
        4'h3: current_number <= sequence_3;
        4'h4: current_number <= sequence_4;
        4'h5: current_number <= sequence_5;
        4'h6: current_number <= sequence_6;
        4'h7: current_number <= sequence_7;
        4'h8: current_number <= sequence_8;
        4'h9: current_number <= sequence_9;
        4'hA: current_number <= sequence_10;
        4'hB: current_number <= sequence_11;
        4'hC: current_number <= sequence_12;
        4'hD: current_number <= sequence_13;
        4'hE: current_number <= sequence_14;
        4'hF: current_number <= sequence_15;
        default: current_number <= 2'b00; 
    endcase
end

endmodule

module dec7seg_4bits_1x2(
    output [6:0] x,
    output [6:0] y,
    input [3:0] a
); 

dec7seg_4bits d0(.x(y), .a( (a > 4'h9) ? a - 4'ha : a));
dec7seg_4bits d1(.x(x), .a((a > 4'h9) ? 4'h1 : 4'h0));

endmodule

module dec7seg_4bits(
  output [6:0] x, 
  input [3:0] a
);

  assign x =  (a == 4'h0) ? 7'b1111110 :
              (a == 4'h1) ? 7'b0110000 :
              (a == 4'h2) ? 7'b1101101 :
              (a == 4'h3) ? 7'b1111001 :
              (a == 4'h4) ? 7'b0110011 :
              (a == 4'h5) ? 7'b1011011 :
              (a == 4'h6) ? 7'b1011111 :
              (a == 4'h7) ? 7'b1110000 :
              (a == 4'h8) ? 7'b1111111 :
              (a == 4'h9) ? 7'b1111011 :
              7'b0000000; 

endmodule

module dec7seg_2bits(
    output [6:0] x, 
    input [1:0] a
);

  assign x = (a == 2'b00) ? 7'b1111110 :
             (a == 2'b01) ? 7'b0110000 :
             (a == 2'b10) ? 7'b1101101 :
             (a == 2'b11) ? 7'b0000000 :
             7'b0000000; 

endmodule

module verify_btn(
    output is_right_choice,
    input [2:0] btn,
    input [1:0] current_number
);

    assign is_right_choice =    (btn[0] && (current_number == 2'b00)) || 
                                (btn[1] && (current_number == 2'b01)) || 
                                (btn[2] && (current_number == 2'b10));

endmodule

module recieve_btn_input(
    output was_some_btn_pressed,
    input [2:0] btn
);

    assign was_some_btn_pressed = btn[0] || btn[1] || btn[2];

endmodule


module shift_leds(
    output [9:0] y,
    input [9:0] x
);

    assign y = x[9] ? 10'b0000000001 : x << 1'b1; 

endmodule
module dec7seg_4bits_hexadec(
    output [6:0] y,    // Saída
    input [3:0] a    // Entrada A
);  

    assign y =  (a == 4'h0) ? 7'b1111110 :
                (a == 4'h1) ? 7'b0110000 :
                (a == 4'h2) ? 7'b1101101 :
                (a == 4'h3) ? 7'b1111001 :
                (a == 4'h4) ? 7'b0110011 :
                (a == 4'h5) ? 7'b1011011 :
                (a == 4'h6) ? 7'b1011111 :
                (a == 4'h7) ? 7'b1110000 :
                (a == 4'h8) ? 7'b1111111 :
                (a == 4'h9) ? 7'b1111011 :
                (a == 4'hA) ? 7'b1110111 :
                (a == 4'hB) ? 7'b0011111 :
                (a == 4'hC) ? 7'b1001110 :
                (a == 4'hD) ? 7'b0111101 :
                (a == 4'hE) ? 7'b1001111 :
                (a == 4'hF) ? 7'b1000111 :
                7'b0000000;
endmodule

test_banch/main_tb.v
`timescale 1ns/1ns
`include "main_simulation.v"

module genius_tb; 
  // Declaração de sinais
  logic clock, start, reset;
  logic btn0, btn1, btn2;
  wire [6:0] segd0;    
  wire [6:0] segd1;    
  wire [6:0] segd2;    
  wire [6:0] segd3;
  wire [9:0] leds;
  logic [9:2] sw;

  // iverilog -o main_tb.vvp main_tb.v && vvp main_tb.vvp && gtkwave genius_tb.vcd

  // Geração de clock com período de 20 ns (50 MHz)
  always begin
     #10 clock = ~clock;
  end
    
  // Testbench
  initial begin
    // Dumpfile para visualização da simulação
    $dumpfile("genius_tb.vcd"); 
    $dumpvars(0, genius_tb);

    // Inicialização dos sinais
    clock = 0;
    reset = 0;
    start = 0;
    btn0 = 0;
    btn1 = 0;
    btn2 = 0;
    sw = 8'b00000000;

    // Sequência de testes


    // 2. Iniciar o jogo
    #10 start = 1; 
    #20 start = 0; 

    // 3. Simular pressionamento dos botões
    #10 btn0 = 1; // Pressionar btn0
    #10 btn0 = 0;  // Soltar btn0

    #10 btn1 = 1; // Pressionar btn1
    #10 btn1 = 0;  // Soltar btn1

    #10 btn2 = 1; // Pressionar btn2
    #10 btn2 = 0;  // Soltar btn2

    // 4. Simulação finalizada
    #10000 $finish;   
  end

  // Instância do módulo genius
  genius genius0(
    .clock(clock),
    .btn({btn2, btn1, btn0}),
    .reset(reset),
    .start(start), 
    .sw(sw),
    .segd0(segd0),  
    .segd1(segd1),  
    .segd2(segd2),  
    .segd3(segd3), 
    .leds(leds)    
  );

endmodule

test_banch/genius_tb.vcd
$date
	Fri Oct 11 15:28:53 2024
$end
$version
	Icarus Verilog
$end
$timescale
	1ns
$end
$scope module genius_tb $end
$var wire 7 ! segd3 [6:0] $end
$var wire 7 " segd2 [6:0] $end
$var wire 7 # segd1 [6:0] $end
$var wire 7 $ segd0 [6:0] $end
$var wire 10 % leds [9:0] $end
$var reg 1 & btn0 $end
$var reg 1 ' btn1 $end
$var reg 1 ( btn2 $end
$var reg 1 ) clock $end
$var reg 1 * reset $end
$var reg 1 + start $end
$var reg 8 , sw [9:2] $end
$scope module genius0 $end
$var wire 3 - btn [2:0] $end
$var wire 1 ) clock $end
$var wire 1 * reset $end
$var wire 1 + start $end
$var wire 8 . sw [9:2] $end
$var wire 1 / was_some_btn_pressed $end
$var wire 10 0 shifted_leds [9:0] $end
$var wire 7 1 segd_3 [6:0] $end
$var wire 7 2 segd_2 [6:0] $end
$var wire 7 3 segd_0 [6:0] $end
$var wire 1 4 is_right_choice $end
$var wire 2 5 current_number [1:0] $end
$var parameter 3 6 add_difficult_state $end
$var parameter 10 7 leds_off $end
$var parameter 10 8 leds_on $end
$var parameter 3 9 receive_inputs_state $end
$var parameter 3 : reset_game_state $end
$var parameter 7 ; seg_off $end
$var parameter 3 < show_sequence_state $end
$var reg 4 = Current_level [3:0] $end
$var reg 4 > Current_number [3:0] $end
$var reg 3 ? Next_state [2:0] $end
$var reg 4 @ Sequence_count [3:0] $end
$var reg 3 A State [2:0] $end
$var reg 1 B clock_count $end
$var reg 4 C current_level [3:0] $end
$var reg 10 D leds [9:0] $end
$var reg 3 E next_state [2:0] $end
$var reg 7 F segd0 [6:0] $end
$var reg 7 G segd1 [6:0] $end
$var reg 7 H segd2 [6:0] $end
$var reg 7 I segd3 [6:0] $end
$var reg 4 J sequence_count [3:0] $end
$var reg 3 K state [2:0] $end
$scope module btn_input $end
$var wire 3 L btn [2:0] $end
$var wire 1 / was_some_btn_pressed $end
$upscope $end
$scope module dec7_2bits $end
$var wire 7 M x [6:0] $end
$var wire 2 N a [1:0] $end
$upscope $end
$scope module dec7seg_4bits_hexadec0 $end
$var wire 4 O a [3:0] $end
$var wire 7 P y [6:0] $end
$upscope $end
$scope module dec7seg_4bits_hexadec1 $end
$var wire 4 Q a [3:0] $end
$var wire 7 R y [6:0] $end
$upscope $end
$scope module seq $end
$var wire 1 ) clk $end
$var wire 4 S sequence_count [3:0] $end
$var wire 1 + start $end
$var parameter 2 T one $end
$var parameter 2 U two $end
$var parameter 2 V zero $end
$var reg 2 W current_number [1:0] $end
$var reg 2 X sequence_0 [1:0] $end
$var reg 2 Y sequence_1 [1:0] $end
$var reg 2 Z sequence_10 [1:0] $end
$var reg 2 [ sequence_11 [1:0] $end
$var reg 2 \ sequence_12 [1:0] $end
$var reg 2 ] sequence_13 [1:0] $end
$var reg 2 ^ sequence_14 [1:0] $end
$var reg 2 _ sequence_15 [1:0] $end
$var reg 2 ` sequence_2 [1:0] $end
$var reg 2 a sequence_3 [1:0] $end
$var reg 2 b sequence_4 [1:0] $end
$var reg 2 c sequence_5 [1:0] $end
$var reg 2 d sequence_6 [1:0] $end
$var reg 2 e sequence_7 [1:0] $end
$var reg 2 f sequence_8 [1:0] $end
$var reg 2 g sequence_9 [1:0] $end
$upscope $end
$scope module shift $end
$var wire 10 h x [9:0] $end
$var wire 10 i y [9:0] $end
$upscope $end
$scope module verifier $end
$var wire 3 j btn [2:0] $end
$var wire 2 k current_number [1:0] $end
$var wire 1 4 is_right_choice $end
$upscope $end
$upscope $end
$upscope $end
$enddefinitions $end
$comment Show the parameter values. $end
$dumpall
b0 V
b10 U
b1 T
b1 <
b0 ;
b0 :
b10 9
b1111111111 8
b0 7
b11 6
$end
#0
$dumpvars
bx k
b0 j
bx i
bx h
bx g
bx f
bx e
bx d
bx c
bx b
bx a
bx `
bx _
bx ^
bx ]
bx \
bx [
bx Z
bx Y
bx X
bx W
bx S
bx R
bx Q
bx P
bx O
bx N
bx M
b0 L
bx K
bx J
bx I
bx H
bx G
bx F
bx E
bx D
bx C
xB
bx A
bx @
bx ?
bx >
bx =
bx 5
04
bx 3
bx 2
bx 1
bx 0
0/
b0 .
b0 -
b0 ,
0+
0*
0)
0(
0'
0&
bx %
bx $
bx #
bx "
bx !
$end
#10
b0 0
b0 i
b1111110 3
b1111110 M
b1 _
b0 ^
b1 ]
b0 \
b10 [
b0 Z
b1 g
b0 f
b10 e
b0 d
b10 c
b0 b
b1 a
b0 `
b1 Y
b10 X
b0 5
b0 N
b0 W
b0 k
b0xx >
b0 E
b0 %
b0 D
b0 h
b0 #
b0 G
1+
1)
#20
0)
#30
b0 >
b0 ?
b0 K
1)
0+
#40
14
1/
0)
b1 -
b1 L
b1 j
1&
#50
b1 0
b1 i
b0 A
b0 $
b0 F
b1111111111 %
b1111111111 D
b1111111111 h
04
0/
1)
b0 -
b0 L
b0 j
0&
#60
1/
0)
b10 -
b10 L
b10 j
1'
#70
0/
1)
b0 -
b0 L
b0 j
0'
#80
1/
0)
b100 -
b100 L
b100 j
1(
#90
0/
1)
b0 -
b0 L
b0 j
0(
